django_celery_tracker/__init__.py
django_celery_tracker/apps.py
django_celery_tracker/decorators.py
django_celery_tracker/helpers.py
django_celery_tracker/models.py
django_celery_tracker/signals.py
django_celery_tracker/urls.py
django_celery_tracker/views.py
django_celery_tracker/migrations/0001_initial.py
django_celery_tracker/migrations/0002_celerytask_args.py
django_celery_tracker/migrations/0003_alter_celerytask_id.py
django_celery_tracker/migrations/__init__.py
django_celery_tracker/static/celery_tracker/css/dashboard.css
django_celery_tracker/static/celery_tracker/fonts/icomoon.ttf
django_celery_tracker/static/celery_tracker/js/dashboard.js
django_celery_tracker/templates/celery_tracker/timeline_dashboard.html
django_celery_tracker-2.1.0.dist-info/LICENSE
django_celery_tracker-2.1.0.dist-info/METADATA
django_celery_tracker-2.1.0.dist-info/WHEEL
django_celery_tracker-2.1.0.dist-info/top_level.txt
django_celery_tracker-2.1.0.dist-info/RECORD
