Metadata-Version: 2.1
Name: django-celery-tracker
Version: 2.1.0
Summary: Celery tracker for Django.
Home-page: https://github.com/chris-allen/django-celery-tracker
Author: Chris Allen
Author-email: chris@apaxsoftware.com
License: MIT
Keywords: celery django events monitoring tracker
Platform: any
Classifier: Development Status :: 5 - Production/Stable
Classifier: License :: OSI Approved :: BSD License
Classifier: Programming Language :: Python
Classifier: Programming Language :: Python :: 3
Classifier: Programming Language :: Python :: 3.8
Classifier: Programming Language :: Python :: 3.10
Classifier: Programming Language :: Python :: Implementation :: CPython
Classifier: Programming Language :: Python :: Implementation :: PyPy
Classifier: Framework :: Django
Classifier: Framework :: Django :: 3.2
Classifier: Framework :: Django :: 4.2
Classifier: Operating System :: OS Independent
Classifier: Topic :: Communications
Classifier: Topic :: System :: Distributed Computing
Classifier: Topic :: Software Development :: Libraries :: Python Modules
License-File: LICENSE
Requires-Dist: Django (>=3.2)
